cabot/__init__.py
cabot/cabot_config.py
cabot/celery.py
cabot/celeryconfig.py
cabot/context_processors.py
cabot/entrypoint.py
cabot/rest_urls.py
cabot/settings.py
cabot/settings_ldap.py
cabot/settings_utils.py
cabot/urls.py
cabot/version.py
cabot/wsgi.py
cabot/.collectstatic/404.111a66abfdb6.html
cabot/.collectstatic/404.html
cabot/.collectstatic/500.b6d637440e31.html
cabot/.collectstatic/500.html
cabot/.collectstatic/502.6560c4d93a6f.html
cabot/.collectstatic/502.html
cabot/.collectstatic/503.f2fcd50cbcf8.html
cabot/.collectstatic/503.html
cabot/.collectstatic/504.39ef2d214567.html
cabot/.collectstatic/504.html
cabot/.collectstatic/favicon.8ae92bfbe511.ico
cabot/.collectstatic/favicon.8ae92bfbe511.ico.gz
cabot/.collectstatic/favicon.ico
cabot/.collectstatic/favicon.ico.gz
cabot/.collectstatic/robots.9152d7f1724e.txt
cabot/.collectstatic/robots.txt
cabot/.collectstatic/staticfiles.json
cabot/.collectstatic/CACHE/manifest.json
cabot/.collectstatic/CACHE/css/eb2f4a56cb57.css
cabot/.collectstatic/CACHE/js/21ea8ffe1e28.js
cabot/.collectstatic/CACHE/js/2a886a88f50d.js
cabot/.collectstatic/CACHE/js/347dd609afe1.js
cabot/.collectstatic/CACHE/js/4d33fede5dbb.js
cabot/.collectstatic/CACHE/js/649531c932e2.js
cabot/.collectstatic/CACHE/js/7d887ddcb2d1.js
cabot/.collectstatic/CACHE/js/86525b16a0d8.js
cabot/.collectstatic/CACHE/js/9de8a7b0f999.js
cabot/.collectstatic/CACHE/js/d655685e1162.js
cabot/.collectstatic/admin/css/base.31652d31b392.css
cabot/.collectstatic/admin/css/base.31652d31b392.css.gz
cabot/.collectstatic/admin/css/base.5af66c1b1797.css
cabot/.collectstatic/admin/css/base.6b517d0d5813.css
cabot/.collectstatic/admin/css/base.6b517d0d5813.css.gz
cabot/.collectstatic/admin/css/base.css
cabot/.collectstatic/admin/css/base.css.gz
cabot/.collectstatic/admin/css/changelists.css
cabot/.collectstatic/admin/css/changelists.css.gz
cabot/.collectstatic/admin/css/changelists.f6dc691f8d62.css
cabot-0.11.12.dist-info/DESCRIPTION.rst
cabot-0.11.12.dist-info/METADATA
cabot-0.11.12.dist-info/RECORD
cabot-0.11.12.dist-info/WHEEL
cabot-0.11.12.dist-info/entry_points.txt
cabot-0.11.12.dist-info/metadata.json
cabot-0.11.12.dist-info/top_level.txt
