Metadata-Version: 2.0
Name: cabot
Version: 0.11.12
Summary: Self-hosted, easily-deployable monitoring and alerts service - like a lightweight PagerDuty
Home-page: http://cabotapp.com
Author: Arachnys
Author-email: info@arachnys.com
License: MIT
Platform: UNKNOWN
Requires-Dist: amqp (==2.1.4)
Requires-Dist: anyjson (==0.3.3)
Requires-Dist: appdirs (==1.4.3)
Requires-Dist: billiard (==3.5.0.2)
Requires-Dist: celery (==4.0.2)
Requires-Dist: coreapi (==2.3.0)
Requires-Dist: coreschema (==0.0.4)
Requires-Dist: dj-database-url (==0.4.2)
Requires-Dist: Django (==1.11.11)
Requires-Dist: django-appconf (==1.0.2)
Requires-Dist: django-auth-ldap (==1.2.16)
Requires-Dist: django-autocomplete-light (==3.2.10)
Requires-Dist: django-compressor (==2.2)
Requires-Dist: django-filter (==1.0.4)
Requires-Dist: django-jsonify (==0.3.0)
Requires-Dist: django-polymorphic (==1.3)
Requires-Dist: djangorestframework (==3.6.2)
Requires-Dist: gevent (==1.2.1)
Requires-Dist: greenlet (==0.4.12)
Requires-Dist: gunicorn (==19.7.1)
Requires-Dist: httplib2 (==0.10.3)
Requires-Dist: icalendar (==3.11.3)
Requires-Dist: itypes (==1.1.0)
Requires-Dist: python-jenkins (==0.4.15)
Requires-Dist: Jinja2 (==2.9.6)
Requires-Dist: kombu (==4.0.2)
Requires-Dist: Markdown (==2.6.8)
Requires-Dist: MarkupSafe (==1.0)
Requires-Dist: packaging (==16.8)
Requires-Dist: psycopg2 (==2.7.1)
Requires-Dist: Pygments (==2.2.0)
Requires-Dist: pyparsing (==2.2.0)
Requires-Dist: PySocks (==1.6.7)
Requires-Dist: python-dateutil (==2.6.0)
Requires-Dist: pytz (==2017.2)
Requires-Dist: rcssmin (==1.0.6)
Requires-Dist: redis (==2.10.5)
Requires-Dist: requests (==2.13.0)
Requires-Dist: rjsmin (==1.0.12)
Requires-Dist: six (==1.10.0)
Requires-Dist: social-auth-app-django (==1.1.0)
Requires-Dist: twilio (==5.7.0)
Requires-Dist: uritemplate (==3.0.0)
Requires-Dist: vine (==1.1.3)
Requires-Dist: whitenoise (==3.3.0)
Requires-Dist: cabot-alert-email (==1.4.3)
Requires-Dist: cabot-alert-hipchat (==2.0.3)
Requires-Dist: cabot-alert-twilio (==1.3.3)
Requires-Dist: cabot-alert-slack (==0.8.3)
Requires-Dist: cabot-check-cloudwatch (==0.1.2)
